understory/code/__init__.py
understory/code/templates/__init__.py
understory/code/templates/index.html
understory/code/templates/project.html
understory/code/templates/project_created.html
understory/code/templates/project_release.html
understory/code/templates/project_release_file.html
understory/code/templates/project_repository_file.html
understory/code/templates/project_settings.html
understory/code/templates/pypi_index.html
understory/code/templates/pypi_project.html
understory/code/templates/template.html
understory_code-0.0.151.dist-info/entry_points.txt
understory_code-0.0.151.dist-info/LICENSE
understory_code-0.0.151.dist-info/WHEEL
understory_code-0.0.151.dist-info/METADATA
understory_code-0.0.151.dist-info/RECORD
