Metadata-Version: 2.1
Name: understory-code
Version: 0.0.151
Summary: Host code in the understory
Home-page: https://ragt.ag/code/understory-code
License: AGPL-3.0-or-later
Keywords: Understory,Git,PyPI
Author: Angelo Gladding
Author-email: angelo@ragt.ag
Requires-Python: >=3.9,<3.11
Classifier: License :: OSI Approved :: GNU Affero General Public License v3 or later (AGPLv3+)
Classifier: Programming Language :: Python :: 3
Classifier: Programming Language :: Python :: 3.9
Requires-Dist: understory (>=0.0,<0.1)
Requires-Dist: warez (>=0.0,<0.1)
Project-URL: Documentation, https://ragt.ag/code/understory-code/docs
Project-URL: Repository, https://ragt.ag/code/understory-code.git
